extractor/__init__.py
extractor/constants/__init__.py
extractor/constants/metadata.py
extractor/extractor.py
extractor/record.py
apple_health_extractor-0.1.6.dist-info/LICENSE
apple_health_extractor-0.1.6.dist-info/METADATA
apple_health_extractor-0.1.6.dist-info/WHEEL
apple_health_extractor-0.1.6.dist-info/RECORD
