Metadata-Version: 2.1
Name: apple-health-extractor
Version: 0.1.6
Summary: This library provides functionality to parse and extract data from the XML exports of Apple Health app, enabling users to analyze and utilize their health data conveniently.
Home-page: https://github.com/martinkelly23/apple-health-extractor
License: MIT
Keywords: data extractor,apple health data
Author: martinkelly23
Author-email: martkelly92@gmail.com
Requires-Python: >=3.8,<4.0
Classifier: License :: OSI Approved :: MIT License
Classifier: Programming Language :: Python :: 3
Classifier: Programming Language :: Python :: 3.8
Classifier: Programming Language :: Python :: 3.9
Classifier: Programming Language :: Python :: 3.10
Classifier: Programming Language :: Python :: 3.11
Classifier: Programming Language :: Python :: 3.12
Requires-Dist: black (>=24.3.0,<25.0.0)
Requires-Dist: pytest (>=8.1.1,<9.0.0)
Requires-Dist: xmltodict (>=0.13.0,<0.14.0)
